[
  {

    "name" : "io.narayana.lra.coordinator.domain.model.LRARecord",
    "allDeclaredConstructors" : true,
    "allPublicConstructors" : true,
    "allDeclaredMethods" : true,
    "allPublicMethods" : true,
    "allDeclaredFields" : true,
    "allPublicFields" : true
  },
  {

    "name" : "com.arjuna.ats.internal.arjuna.coordinator.CheckedActionFactoryImple",
    "allDeclaredConstructors" : true,
    "allPublicConstructors" : true,
    "allDeclaredMethods" : true,
    "allPublicMethods" : true,
    "allDeclaredFields" : true,
    "allPublicFields" : true
  },
  {

    "name" : "com.arjuna.ats.internal.arjuna.objectstore.ShadowNoFileLockStore",
    "allDeclaredConstructors" : true,
    "allPublicConstructors" : true,
    "allDeclaredMethods" : true,
    "allPublicMethods" : true,
    "allDeclaredFields" : true,
    "allPublicFields" : true
  },
  {

    "name" : "com.arjuna.ats.arjuna.recovery.ActionStatusService",
    "allDeclaredConstructors" : true,
    "allPublicConstructors" : true,
    "allDeclaredMethods" : true,
    "allPublicMethods" : true,
    "allDeclaredFields" : true,
    "allPublicFields" : true
  },
  {

    "name" : "com.arjuna.ats.arjuna.common.ObjectStoreEnvironmentBean",
    "allDeclaredConstructors" : true,
    "allPublicConstructors" : true,
    "allDeclaredMethods" : true,
    "allPublicMethods" : true,
    "allDeclaredFields" : true,
    "allPublicFields" : true
  },
  {

    "name" : "com.arjuna.ats.arjuna.common.MetaObjectStoreEnvironmentBean",
    "allDeclaredConstructors" : true,
    "allPublicConstructors" : true,
    "allDeclaredMethods" : true,
    "allPublicMethods" : true,
    "allDeclaredFields" : true,
    "allPublicFields" : true
  }
]
